agliooglio/__init__.py
agliooglio/errors.py
agliooglio/octarin.py
agliooglio/params.py
agliooglio/utils.py
agliooglio/utils_hash.py
agliooglio/datasets/__init__.py
agliooglio/datasets/base_dataset.py
agliooglio/datasets/datasets.py
agliooglio/datasets/utils.py
octarin/__init__.py
octarin/errors.py
octarin/octarin.py
octarin/params.py
octarin/utils.py
octarin/utils_hash.py
octarin/datasets/__init__.py
octarin/datasets/base_dataset.py
octarin/datasets/datasets.py
octarin/datasets/utils.py
aglioolio-0.0.1.dist-info/LICENSE
aglioolio-0.0.1.dist-info/METADATA
aglioolio-0.0.1.dist-info/WHEEL
aglioolio-0.0.1.dist-info/top_level.txt
aglioolio-0.0.1.dist-info/RECORD
